LICENSE
MANIFEST.in
README.rst
VERSION
setup.py
blast/__init__.py
blast/main.py
blast/scanner.py
blast.egg-info/PKG-INFO
blast.egg-info/SOURCES.txt
blast.egg-info/dependency_links.txt
blast.egg-info/entry_points.txt
blast.egg-info/not-zip-safe
blast.egg-info/requires.txt
blast.egg-info/top_level.txt
blast/static/blast.css
blast/static/blast.js
blast/static/bootstrap-modal.css
blast/static/bootstrap-modal.js
blast/static/close.png
blast/static/favicon.ico
blast/static/flashblock.css
blast/static/jquery-1.7.2.min.js
blast/static/jquery-ui-1.8.22.custom.min.js
blast/static/jquery.shuffle.js
blast/static/page-player.css
blast/static/page-player.js
blast/static/sm2.js
blast/static/sticky.css
blast/static/sticky.js
blast/static/swf/soundmanager2.swf
blast/static/swf/soundmanager2_debug.swf
blast/static/swf/soundmanager2_flash9.swf
blast/static/swf/soundmanager2_flash9_debug.swf
blast/static/swf/soundmanager2_flash_xdomain.zip
blast/templates/401.html
blast/templates/404.html
blast/templates/500.html
blast/templates/dupes.html
blast/templates/play.html