Metadata-Version: 1.0
Name: blast
Version: 0.3.0
Summary: a simple web-based, multi-platform music/mp3 player written in python, HTML/CSS and javascript
Home-page: http://github.com/kwlzn/blast
Author: kw
Author-email: pypi@onoku.com
License: BSD
Keywords: python wsgi web mp3 player javascript html music audio
Platform: UNKNOWN
Classifier: Development Status :: 4 - Beta
Classifier: License :: OSI Approved :: BSD License
Classifier: Environment :: Console
Classifier: Environment :: Web Environment
Classifier: Operating System :: OS Independent
Classifier: Programming Language :: Python
Classifier: Programming Language :: JavaScript
Classifier: Topic :: Multimedia :: Sound/Audio :: Players :: MP3
Classifier: Topic :: Internet :: WWW/HTTP :: WSGI
Classifier: Topic :: Internet :: WWW/HTTP :: WSGI :: Application
Classifier: Topic :: Internet :: WWW/HTTP
Classifier: Topic :: Software Development :: Libraries :: Python Modules
